bibtags/__init__.py
bibtags/bibtags.py
bibtags/cli.py
bibtags-0.3.0.dist-info/AUTHORS.rst
bibtags-0.3.0.dist-info/LICENSE
bibtags-0.3.0.dist-info/METADATA
bibtags-0.3.0.dist-info/WHEEL
bibtags-0.3.0.dist-info/entry_points.txt
bibtags-0.3.0.dist-info/top_level.txt
bibtags-0.3.0.dist-info/RECORD
