Metadata-Version: 2.1
Name: bibtags
Version: 0.3.0
Summary: tags for bib
Home-page: https://github.com/volodymyrss/bibtags
Author: Volodymyr SAVCHENKO
Author-email: contact@volodymyrsavchenko.com
License: BSD license
Keywords: bibtags
Platform: UNKNOWN
Classifier: Development Status :: 2 - Pre-Alpha
Classifier: Intended Audience :: Developers
Classifier: License :: OSI Approved :: BSD License
Classifier: Natural Language :: English
Classifier: Programming Language :: Python :: 3
Classifier: Programming Language :: Python :: 3.5
Classifier: Programming Language :: Python :: 3.6
Classifier: Programming Language :: Python :: 3.7
Classifier: Programming Language :: Python :: 3.8
Requires-Python: >=3.5
Requires-Dist: Click (>=7.0)
